flask_pay/__init__.py
Flask_PAY-0.60.dist-info/LICENSE
Flask_PAY-0.60.dist-info/METADATA
Flask_PAY-0.60.dist-info/WHEEL
Flask_PAY-0.60.dist-info/top_level.txt
Flask_PAY-0.60.dist-info/RECORD
