Metadata-Version: 2.1
Name: Flask-PAY
Version: 0.60
Summary: flask-pay
Home-page: 
Author: 浩
Author-email: 
License: GPL
Keywords: flask extension development pay
Platform: any
Classifier: Programming Language :: Python :: 3
License-File: LICENSE
Requires-Dist: Flask
Requires-Dist: wechatpayv3
